{
  "$schema": "https://developer.microsoft.com/json-schemas/fabric/item/report/definition/visualContainer/2.10.0/schema.json",
  "name": "ab5db896ded6ae3d31f0",
  "position": {
    "x": 394.63917525773195,
    "y": 0,
    "z": 2000,
    "height": 360,
    "width": 617.93814432989689,
    "tabOrder": 2000
  },
  "visual": {
    "visualType": "columnChart",
    "query": {
      "queryState": {
        "Category": {
          "projections": [
            {
              "field": {
                "Column": {
                  "Expression": {
                    "SourceRef": {
                      "Entity": "dim_category"
                    }
                  },
                  "Property": "category"
                }
              },
              "queryRef": "dim_category.category",
              "nativeQueryRef": "category",
              "active": true
            }
          ]
        },
        "Y": {
          "projections": [
            {
              "field": {
                "Measure": {
                  "Expression": {
                    "SourceRef": {
                      "Entity": "Mesures"
                    }
                  },
                  "Property": "% Positive Reviews"
                }
              },
              "queryRef": "Mesures.% Positive Reviews",
              "nativeQueryRef": "% Positive Reviews"
            }
          ]
        }
      },
      "sortDefinition": {
        "sort": [
          {
            "field": {
              "Measure": {
                "Expression": {
                  "SourceRef": {
                    "Entity": "Mesures"
                  }
                },
                "Property": "% Positive Reviews"
              }
            },
            "direction": "Descending"
          }
        ],
        "isDefaultSort": true
      }
    },
    "visualContainerObjects": {
      "title": [
        {
          "properties": {
            "fontSize": {
              "expr": {
                "Literal": {
                  "Value": "12D"
                }
              }
            },
            "heading": {
              "expr": {
                "Literal": {
                  "Value": "'Heading2'"
                }
              }
            },
            "bold": {
              "expr": {
                "Literal": {
                  "Value": "true"
                }
              }
            },
            "fontColor": {
              "solid": {
                "color": {
                  "expr": {
                    "ThemeDataColor": {
                      "ColorId": 1,
                      "Percent": 0.2
                    }
                  }
                }
              }
            },
            "text": {
              "expr": {
                "Literal": {
                  "Value": "'Which categories have the happiest reviewers?'"
                }
              }
            }
          }
        }
      ]
    },
    "drillFilterOtherVisuals": true
  },
  "filterConfig": {
    "filters": [
      {
        "name": "3e59557d91af49ba04b5",
        "field": {
          "Column": {
            "Expression": {
              "SourceRef": {
                "Entity": "dim_category"
              }
            },
            "Property": "category"
          }
        },
        "type": "Categorical"
      },
      {
        "name": "55bae6e3caccfc774738",
        "field": {
          "Measure": {
            "Expression": {
              "SourceRef": {
                "Entity": "Mesures"
              }
            },
            "Property": "% Positive Reviews"
          }
        },
        "type": "Advanced"
      }
    ]
  }
}